{
    "nodes": [
        {"id": "Fall Semester Kick-off", "group": 3, "size": "16", "fx": 10, "fy": 10, "fz": 10},
        {"id": "Late Night Study Session", "group": 3, "size": "10", "fx": -260, "fy": -160, "fz": 60},
        {"id": "Algorithms Midterm", "group": 3, "size": "12", "fx": -410, "fy": -260, "fz": 110},
        {"id": "CS Project Deadline", "group": 3, "size": "12", "fx": -420, "fy": -240, "fz": 120},
        {"id": "General Chemistry Lecture", "group": 3, "size": "8", "fx": -360, "fy": -110, "fz": 90},
        {"id": "Cell Biology Lab Work", "group": 3, "size": "8", "fx": -110, "fy": -310, "fz": 130},
        {"id": "Dorm Move-in Day", "group": 3, "size": "14", "fx": 310, "fy": 210, "fz": -110},
        {"id": "Friday Movie Night", "group": 3, "size": "10", "fx": 330, "fy": 230, "fz": -80},
        {"id": "Team Lunch", "group": 3, "size": "8", "fx": 210, "fy": 110, "fz": -40},
        {"id": "Morning Workout", "group": 3, "size": "8", "fx": 460, "fy": -110, "fz": 10},
        {"id": "Swim Practice", "group": 3, "size": "8", "fx": 510, "fy": -160, "fz": 30},
        {"id": "Tennis Match", "group": 3, "size": "10", "fx": 510, "fy": -60, "fz": -10},
        {"id": "Student Gov. Meeting", "group": 3, "size": "10", "fx": 10, "fy": 260, "fz": -140},
        {"id": "Drama Club Rehearsal", "group": 3, "size": "8", "fx": -40, "fy": 360, "fz": -170},
        {"id": "Coffee & Code Meetup", "group": 3, "size": "10", "fx": -210, "fy": 410, "fz": 210},
        {"id": "Poetry Reading Night", "group": 3, "size": "8", "fx": -260, "fy": 460, "fz": 230},
        {"id": "Weekend Picnic", "group": 3, "size": "10", "fx": 10, "fy": -410, "fz": -190},
        {"id": "Internship Interview", "group": 3, "size": "12", "fx": 410, "fy": 410, "fz": 310},
        {"id": "Final Project Presentation", "group": 3, "size": "14", "fx": 420, "fy": 390, "fz": 320},
        {"id": "Pottery Class", "group": 3, "size": "8", "fx": 210, "fy": -310, "fz": 160},
        {"id": "Orchestra Concert", "group": 3, "size": "12", "fx": 260, "fy": -360, "fz": 190},
        {"id": "Resume Workshop", "group": 3, "size": "10", "fx": -160, "fy": 160, "fz": -30},
        {"id": "Spring Formal", "group": 3, "size": "14", "fx": 20, "fy": 270, "fz": -160},
        {"id": "Club Fair", "group": 3, "size": "12", "fx": 20, "fy": 20, "fz": 20},
        {"id": "Hackathon", "group": 3, "size": "14", "fx": -430, "fy": -270, "fz": 90},
        {"id": "Final Exams Week", "group": 3, "size": "16", "fx": -270, "fy": -170, "fz": 40},
        {"id": "Graduation Ceremony", "group": 3, "size": "18", "fx": 30, "fy": -30, "fz": 0},

        {"id": "Main Campus Quad", "group": 4, "size": "25", "fx": 0, "fy": 0, "fz": 0},
        {"id": "University Library", "group": 4, "size": "20", "fx": -250, "fy": -150, "fz": 50},
        {"id": "Computer Science Dept.", "group": 4, "size": "18", "fx": -400, "fy": -250, "fz": 100},
        {"id": "Lecture Hall B", "group": 4, "size": "15", "fx": -350, "fy": -100, "fz": 80},
        {"id": "Biology Lab", "group": 4, "size": "15", "fx": -100, "fy": -300, "fz": 120},
        {"id": "Student Dormitory 'Oak Hall'", "group": 4, "size": "20", "fx": 300, "fy": 200, "fz": -100},
        {"id": "Dorm Common Room", "group": 4, "size": "12", "fx": 320, "fy": 220, "fz": -90},
        {"id": "Dining Commons", "group": 4, "size": "18", "fx": 200, "fy": 100, "fz": -50},
        {"id": "Recreation Center", "group": 4, "size": "18", "fx": 450, "fy": -100, "fz": 0},
        {"id": "University Pool", "group": 4, "size": "15", "fx": 500, "fy": -150, "fz": 20},
        {"id": "Tennis Courts", "group": 4, "size": "15", "fx": 500, "fy": -50, "fz": -20},
        {"id": "Student Union", "group": 4, "size": "18", "fx": 0, "fy": 250, "fz": -150},
        {"id": "Campus Theater", "group": 4, "size": "15", "fx": -50, "fy": 350, "fz": -180},
        {"id": "Off-Campus Coffee Shop", "group": 4, "size": "12", "fx": -200, "fy": 400, "fz": 200},
        {"id": "Local Bookstore", "group": 4, "size": "12", "fx": -250, "fy": 450, "fz": 220},
        {"id": "City Park", "group": 4, "size": "15", "fx": 0, "fy": -400, "fz": -200},
        {"id": "Internship Office 'TechCorp'", "group": 4, "size": "18", "fx": 400, "fy": 400, "fz": 300},
        {"id": "Art Studio", "group": 4, "size": "15", "fx": 200, "fy": -300, "fz": 150},
        {"id": "Music Hall", "group": 4, "size": "15", "fx": 250, "fy": -350, "fz": 180},
        {"id": "Career Services Center", "group": 4, "size": "12", "fx": -150, "fy": 150, "fz": -40},
        {"id": "-1", "group": 5, "size": "40", "color": "light-purple"},



        {"id": "Alex Johnson", "group": 2, "size": "18"},
        {"id": "Brenda Smith", "group": 2, "size": "12"},
        {"id": "Carlos Garcia", "group": 2, "size": "12"},
        {"id": "Diana Chen", "group": 2, "size": "12"},
        {"id": "Ethan Williams", "group": 2, "size": "10"},
        {"id": "Fiona Rodriguez", "group": 2, "size": "10"},
        {"id": "George Miller", "group": 2, "size": "10"},
        {"id": "Hannah Davis", "group": 2, "size": "10"},
        {"id": "Ivan Petrov", "group": 2, "size": "8"},
        {"id": "Jessica Lee", "group": 2, "size": "8"},
        {"id": "Kevin Moore", "group": 2, "size": "8"},
        {"id": "Laura Taylor", "group": 2, "size": "8"},
        {"id": "Michael Brown", "group": 2, "size": "8"},
        {"id": "Nancy Wilson", "group": 2, "size": "8"},
        {"id": "Olivia Martin", "group": 2, "size": "8"},
        {"id": "Peter Anderson", "group": 2, "size": "8"},
        {"id": "Quinn Thompson", "group": 2, "size": "8"},
        {"id": "Rachel White", "group": 2, "size": "8"},
        {"id": "Steven Harris", "group": 2, "size": "8"},
        {"id": "Tina Clark", "group": 2, "size": "8"},
        {"id": "Umar Khan", "group": 2, "size": "8"},
        {"id": "Violet Lewis", "group": 2, "size": "8"},
        {"id": "Walter Hall", "group": 2, "size": "8"},
        {"id": "Xena Young", "group": 2, "size": "8"},
        {"id": "Yara Allen", "group": 2, "size": "8"},
        {"id": "Zachary King", "group": 2, "size": "8"},
        {"id": "Prof. Evelyn Reed", "group": 2, "size": "14"},
        {"id": "Prof. Brian Carter", "group": 2, "size": "14"},
        {"id": "Dr. Susan Wright", "group": 2, "size": "14"},
        {"id": "Coach Miller", "group": 2, "size": "14"},
        {"id": "TA David", "group": 2, "size": "10"},
        {"id": "RA Maria", "group": 2, "size": "10"},
        {"id": "Manager at TechCorp", "group": 2, "size": "14"},
        {"id": "Librarian Mr. Evans", "group": 2, "size": "10"},
        {"id": "Roommate Sam", "group": 2, "size": "12"},
        {"id": "Lab Partner Chloe", "group": 2, "size": "10"},
        {"id": "Mom", "group": 2, "size": "10"},
        {"id": "Dad", "group": 2, "size": "10"},
        {"id": "Sibling Jordan", "group": 2, "size": "10"},
        {"id": "Friend from Home", "group": 2, "size": "10"},
        {"id": "Aaron Bell", "group": 2, "size": "8"},
        {"id": "Abigail Coleman", "group": 2, "size": "8"},
        {"id": "Adam Cox", "group": 2, "size": "8"},
        {"id": "Alice Flores", "group": 2, "size": "8"},
        {"id": "Andrew Foster", "group": 2, "size": "8"},
        {"id": "Angela Gray", "group": 2, "size": "8"},
        {"id": "Anthony Griffin", "group": 2, "size": "8"},
        {"id": "Barbara Hayes", "group": 2, "size": "8"},
        {"id": "Benjamin Howard", "group": 2, "size": "8"},
        {"id": "Betty Hughes", "group": 2, "size": "8"},
        {"id": "Brandon James", "group": 2, "size": "8"},
        {"id": "Brenda Jenkins", "group": 2, "size": "8"},
        {"id": "Brian Johnson", "group": 2, "size": "8"},
        {"id": "Carol Kelly", "group": 2, "size": "8"},
        {"id": "Charles Kim", "group": 2, "size": "8"},
        {"id": "Cynthia Long", "group": 2, "size": "8"},
        {"id": "Daniel Lopez", "group": 2, "size": "8"},
        {"id": "David Mitchell", "group": 2, "size": "8"},
        {"id": "Deborah Morgan", "group": 2, "size": "8"},
        {"id": "Dennis Murphy", "group": 2, "size": "8"},
        {"id": "Donald Murray", "group": 2, "size": "8"},
        {"id": "Donna Myers", "group": 2, "size": "8"},
        {"id": "Edward Nelson", "group": 2, "size": "8"},
        {"id": "Elizabeth Ortiz", "group": 2, "size": "8"},
        {"id": "Frank Parker", "group": 2, "size": "8"},
        {"id": "Gary Perry", "group": 2, "size": "8"},
        {"id": "George Peterson", "group": 2, "size": "8"},
        {"id": "Helen Phillips", "group": 2, "size": "8"},
        {"id": "Henry Powell", "group": 2, "size": "8"},
        {"id": "Irene Price", "group": 2, "size": "8"},
        {"id": "Jack Reed", "group": 2, "size": "8"},
        {"id": "James Richardson", "group": 2, "size": "8"},
        {"id": "Janet Rivera", "group": 2, "size": "8"},
        {"id": "Jason Rogers", "group": 2, "size": "8"},
        {"id": "Jerry Ross", "group": 2, "size": "8"},
        {"id": "Joan Russell", "group": 2, "size": "8"},
        {"id": "Joe Sanchez", "group": 2, "size": "8"},
        {"id": "John Sanders", "group": 2, "size": "8"},
        {"id": "Joyce Scott", "group": 2, "size": "8"},
        {"id": "Judith Simmons", "group": 2, "size": "8"},
        {"id": "Julie Stewart", "group": 2, "size": "8"},
        {"id": "Justin Stone", "group": 2, "size": "8"},
        {"id": "Karen Sullivan", "group": 2, "size": "8"},
        {"id": "Katherine Taylor", "group": 2, "size": "8"},
        {"id": "Keith Thomas", "group": 2, "size": "8"},
        {"id": "Kelly Thompson", "group": 2, "size": "8"},
        {"id": "Kenneth Turner", "group": 2, "size": "8"},
        {"id": "Kimberly Walker", "group": 2, "size": "8"},
        {"id": "Larry Watson", "group": 2, "size": "8"},
        {"id": "Laura West", "group": 2, "size": "8"}




    ],
    "links": [
        { "source": "Algorithms Midterm", "target": "Lecture Hall B", "value": 10 },
        { "source": "CS Project Deadline", "target": "Computer Science Dept.", "value": 10 },
        { "source": "General Chemistry Lecture", "target": "Lecture Hall B", "value": 10 },
        { "source": "Cell Biology Lab Work", "target": "Biology Lab", "value": 10 },
        { "source": "Dorm Move-in Day", "target": "Student Dormitory 'Oak Hall'", "value": 10 },
        { "source": "Friday Movie Night", "target": "Dorm Common Room", "value": 10 },
        { "source": "Team Lunch", "target": "Dining Commons", "value": 10 },
        { "source": "Morning Workout", "target": "Recreation Center", "value": 10 },
        { "source": "Swim Practice", "target": "University Pool", "value": 10 },
        { "source": "Tennis Match", "target": "Tennis Courts", "value": 10 },
        { "source": "Student Gov. Meeting", "target": "Student Union", "value": 10 },
        { "source": "Drama Club Rehearsal", "target": "Campus Theater", "value": 10 },
        { "source": "Coffee & Code Meetup", "target": "Off-Campus Coffee Shop", "value": 10 },
        { "source": "Poetry Reading Night", "target": "Local Bookstore", "value": 10 },
        { "source": "Weekend Picnic", "target": "City Park", "value": 10 },
        { "source": "Internship Interview", "target": "Internship Office 'TechCorp'", "value": 10 },
        { "source": "Final Project Presentation", "target": "Internship Office 'TechCorp'", "value": 10 },
        { "source": "Pottery Class", "target": "Art Studio", "value": 10 },
        { "source": "Orchestra Concert", "target": "Music Hall", "value": 10 },
        { "source": "Resume Workshop", "target": "Career Services Center", "value": 10 },
        { "source": "Spring Formal", "target": "Student Union", "value": 10 },
        { "source": "Club Fair", "target": "Main Campus Quad", "value": 10 },
        { "source": "Hackathon", "target": "Computer Science Dept.", "value": 10 },
        { "source": "Late Night Study Session", "target": "University Library", "value": 10 },
        { "source": "Final Exams Week", "target": "University Library", "value": 10 },
        { "source": "Graduation Ceremony", "target": "Main Campus Quad", "value": 10 },
        { "source": "Fall Semester Kick-off", "target": "Main Campus Quad", "value": 10 },
        { "source": "Student Dormitory 'Oak Hall'", "target": "Dining Commons", "value": 1, "distance": 150 },
        { "source": "Computer Science Dept.", "target": "Lecture Hall B", "value": 1, "distance": 80 },
        { "source": "University Library", "target": "Main Campus Quad", "value": 1, "distance": 100 },
        { "source": "Recreation Center", "target": "University Pool", "value": 1, "distance": 50 },
        { "source": "Student Union", "target": "Main Campus Quad", "value": 1, "distance": 120 },
        { "source": "Art Studio", "target": "Music Hall", "value": 1, "distance": 70 },
        { "source": "Dorm Move-in Day", "target": "Fall Semester Kick-off", "value": 3 },
        { "source": "Fall Semester Kick-off", "target": "Club Fair", "value": 3 },
        { "source": "Late Night Study Session", "target": "Algorithms Midterm", "value": 5 },
        { "source": "Algorithms Midterm", "target": "Final Exams Week", "value": 2 },
        { "source": "Club Fair", "target": "Drama Club Rehearsal", "value": 2 },
        { "source": "Resume Workshop", "target": "Internship Interview", "value": 4 },
        { "source": "Internship Interview", "target": "Final Project Presentation", "value": 4 },
        { "source": "Hackathon", "target": "CS Project Deadline", "value": 3 },
        { "source": "Morning Workout", "target": "Swim Practice", "value": 2 },
        { "source": "Pottery Class", "target": "Orchestra Concert", "value": 1 },
        { "source": "Alex Johnson", "target": "Brenda Smith", "value": 8 },
        { "source": "Alex Johnson", "target": "Carlos Garcia", "value": 8 },
        { "source": "Alex Johnson", "target": "Diana Chen", "value": 7 },
        { "source": "Brenda Smith", "target": "Carlos Garcia", "value": 6 },
        { "source": "Brenda Smith", "target": "Diana Chen", "value": 6 },
        { "source": "Carlos Garcia", "target": "Diana Chen", "value": 5 },
        { "source": "Alex Johnson", "target": "Roommate Sam", "value": 9 },
        { "source": "Roommate Sam", "target": "Student Dormitory 'Oak Hall'", "value": 7 },
        { "source": "Alex Johnson", "target": "Lab Partner Chloe", "value": 6 },
        { "source": "Lab Partner Chloe", "target": "Cell Biology Lab Work", "value": 5 },
        { "source": "Prof. Evelyn Reed", "target": "Computer Science Dept.", "value": 8 },
        { "source": "Prof. Brian Carter", "target": "Biology Lab", "value": 8 },
        { "source": "Alex Johnson", "target": "Prof. Evelyn Reed", "value": 4 },
        { "source": "Alex Johnson", "target": "Prof. Brian Carter", "value": 3 },
        { "source": "Prof. Evelyn Reed", "target": "TA David", "value": 6 },
        { "source": "TA David", "target": "Algorithms Midterm", "value": 4 },
        { "source": "Coach Miller", "target": "Recreation Center", "value": 7 },
        { "source": "Coach Miller", "target": "Swim Practice", "value": 6 },
        { "source": "RA Maria", "target": "Student Dormitory 'Oak Hall'", "value": 7 },
        { "source": "RA Maria", "target": "Dorm Move-in Day", "value": 5 },
        { "source": "Manager at TechCorp", "target": "Internship Office 'TechCorp'", "value": 8 },
        { "source": "Alex Johnson", "target": "Manager at TechCorp", "value": 5 },
        { "source": "Manager at TechCorp", "target": "Final Project Presentation", "value": 6 },
        { "source": "Librarian Mr. Evans", "target": "University Library", "value": 7 },
        { "source": "Alex Johnson", "target": "Mom", "value": 5 },
        { "source": "Alex Johnson", "target": "Dad", "value": 5 },
        { "source": "Alex Johnson", "target": "Sibling Jordan", "value": 6 },
        { "source": "Ethan Williams", "target": "Fiona Rodriguez", "value": 5 },
        { "source": "George Miller", "target": "Hannah Davis", "value": 5 },
        { "source": "Ivan Petrov", "target": "Jessica Lee", "value": 4 },
        { "source": "Kevin Moore", "target": "Laura Taylor", "value": 4 },
        { "source": "Michael Brown", "target": "Nancy Wilson", "value": 5 },
        { "source": "Olivia Martin", "target": "Peter Anderson", "value": 6 },
        { "source": "Quinn Thompson", "target": "Rachel White", "value": 5 },
        { "source": "Steven Harris", "target": "Tina Clark", "value": 4 },
        { "source": "Umar Khan", "target": "Violet Lewis", "value": 5 },
        { "source": "Walter Hall", "target": "Xena Young", "value": 4 },
        { "source": "Yara Allen", "target": "Zachary King", "value": 5 },
        { "source": "Aaron Bell", "target": "Abigail Coleman", "value": 5 },
        { "source": "Adam Cox", "target": "Alice Flores", "value": 4 },
        { "source": "Andrew Foster", "target": "Angela Gray", "value": 5 },
        { "source": "Anthony Griffin", "target": "Barbara Hayes", "value": 4 },
        { "source": "Benjamin Howard", "target": "Betty Hughes", "value": 5 },
        { "source": "Brandon James", "target": "Brenda Jenkins", "value": 6 },
        { "source": "Brian Johnson", "target": "Carol Kelly", "value": 5 },
        { "source": "Charles Kim", "target": "Cynthia Long", "value": 4 },
        { "source": "Daniel Lopez", "target": "David Mitchell", "value": 5 },
        { "source": "Deborah Morgan", "target": "Dennis Murphy", "value": 4 },
        { "source": "Donald Murray", "target": "Donna Myers", "value": 5 },
        { "source": "Edward Nelson", "target": "Elizabeth Ortiz", "value": 6 },
        { "source": "Frank Parker", "target": "Gary Perry", "value": 5 },
        { "source": "George Peterson", "target": "Helen Phillips", "value": 4 },
        { "source": "Henry Powell", "target": "Irene Price", "value": 5 },
        { "source": "Jack Reed", "target": "James Richardson", "value": 4 },
        { "source": "Janet Rivera", "target": "Jason Rogers", "value": 5 },
        { "source": "Jerry Ross", "target": "Joan Russell", "value": 6 },
        { "source": "Joe Sanchez", "target": "John Sanders", "value": 5 },
        { "source": "Joyce Scott", "target": "Judith Simmons", "value": 4 },
        { "source": "Julie Stewart", "target": "Justin Stone", "value": 5 },
        { "source": "Karen Sullivan", "target": "Katherine Taylor", "value": 4 },
        { "source": "Keith Thomas", "target": "Kelly Thompson", "value": 5 },
        { "source": "Kenneth Turner", "target": "Kimberly Walker", "value": 6 },
        { "source": "Larry Watson", "target": "Laura West", "value": 5 },
        { "source": "Brenda Smith", "target": "Fiona Rodriguez", "value": 2 },
        { "source": "Carlos Garcia", "target": "Steven Harris", "value": 1 },
        { "source": "Diana Chen", "target": "Umar Khan", "value": 2 },
        { "source": "Prof. Evelyn Reed", "target": "Manager at TechCorp", "value": 3 },
        { "source": "Coach Miller", "target": "RA Maria", "value": 2 },
        { "source": "Roommate Sam", "target": "Carlos Garcia", "value": 3 },
        { "source": "Lab Partner Chloe", "target": "Diana Chen", "value": 3 },
        { "source": "Ethan Williams", "target": "Hackathon", "value": 4 },
        { "source": "Fiona Rodriguez", "target": "Hackathon", "value": 4 },
        { "source": "George Miller", "target": "Swim Practice", "value": 3 },
        { "source": "Hannah Davis", "target": "Swim Practice", "value": 3 },
        { "source": "Ivan Petrov", "target": "Drama Club Rehearsal", "value": 2 },
        { "source": "Jessica Lee", "target": "Drama Club Rehearsal", "value": 2 },
        { "source": "Kevin Moore", "target": "Orchestra Concert", "value": 3 },
        { "source": "Laura Taylor", "target": "Orchestra Concert", "value": 3 },
        { "source": "Michael Brown", "target": "Tennis Match", "value": 4 },
        { "source": "Nancy Wilson", "target": "Tennis Match", "value": 4 },
        { "source": "Olivia Martin", "target": "Student Gov. Meeting", "value": 5 },
        { "source": "Peter Anderson", "target": "Student Gov. Meeting", "value": 5 },
        { "source": "Quinn Thompson", "target": "Poetry Reading Night", "value": 3 },
        { "source": "Rachel White", "target": "Poetry Reading Night", "value": 3 },
        { "source": "Steven Harris", "target": "Coffee & Code Meetup", "value": 4 },
        { "source": "Tina Clark", "target": "Coffee & Code Meetup", "value": 4 },
        { "source": "Umar Khan", "target": "Pottery Class", "value": 2 },
        { "source": "Violet Lewis", "target": "Pottery Class", "value": 2 },
        { "source": "Walter Hall", "target": "Resume Workshop", "value": 3 },
        { "source": "Xena Young", "target": "Resume Workshop", "value": 3 },
        { "source": "Yara Allen", "target": "Club Fair", "value": 4 },
        { "source": "Zachary King", "target": "Club Fair", "value": 4 },
        { "source": "Alex Johnson", "target": "Student Dormitory 'Oak Hall'", "value": 7 },
        { "source": "Alex Johnson", "target": "University Library", "value": 6 },
        { "source": "Alex Johnson", "target": "Computer Science Dept.", "value": 5 },
        { "source": "Alex Johnson", "target": "Dining Commons", "value": 6 },
        { "source": "Alex Johnson", "target": "Recreation Center", "value": 4 },
        { "source": "Alex Johnson", "target": "Student Union", "value": 5 },
        { "source": "Alex Johnson", "target": "Off-Campus Coffee Shop", "value": 3 },
        { "source": "Alex Johnson", "target": "Internship Office 'TechCorp'", "value": 4 },
        { "source": "Brenda Smith", "target": "University Library", "value": 5 },
        { "source": "Carlos Garcia", "target": "Computer Science Dept.", "value": 5 },
        { "source": "Diana Chen", "target": "Biology Lab", "value": 4 },
        { "source": "Roommate Sam", "target": "Dorm Common Room", "value": 6 },
        { "source": "Lab Partner Chloe", "target": "Biology Lab", "value": 6 },
        { "source": "TA David", "target": "Computer Science Dept.", "value": 5 },
        { "source": "RA Maria", "target": "Dorm Common Room", "value": 5 },
        { "source": "Librarian Mr. Evans", "target": "Local Bookstore", "value": 4 },
        { "source": "Alex Johnson", "target": "Fall Semester Kick-off", "value": 5 },
        { "source": "Alex Johnson", "target": "Late Night Study Session", "value": 4 },
        { "source": "Alex Johnson", "target": "Algorithms Midterm", "value": 3 },
        { "source": "Alex Johnson", "target": "CS Project Deadline", "value": 3 },
        { "source": "Alex Johnson", "target": "Cell Biology Lab Work", "value": 3 },
        { "source": "Alex Johnson", "target": "Friday Movie Night", "value": 5 },
        { "source": "Alex Johnson", "target": "Morning Workout", "value": 2 },
        { "source": "Alex Johnson", "target": "Internship Interview", "value": 4 },
        { "source": "Alex Johnson", "target": "Final Project Presentation", "value": 5 },
        { "source": "Alex Johnson", "target": "Resume Workshop", "value": 3 },
        { "source": "Alex Johnson", "target": "Spring Formal", "value": 5 },
        { "source": "Alex Johnson", "target": "Club Fair", "value": 4 },
        { "source": "Alex Johnson", "target": "Hackathon", "value": 5 },
        { "source": "Alex Johnson", "target": "Final Exams Week", "value": 4 },
        { "source": "Alex Johnson", "target": "Graduation Ceremony", "value": 5 },
        { "source": "Brenda Smith", "target": "Fall Semester Kick-off", "value": 5 },
        { "source": "Carlos Garcia", "target": "Fall Semester Kick-off", "value": 5 },
        { "source": "Diana Chen", "target": "Fall Semester Kick-off", "value": 5 },
        { "source": "Roommate Sam", "target": "Friday Movie Night", "value": 5 },
        { "source": "Brenda Smith", "target": "Late Night Study Session", "value": 4 },
        { "source": "Carlos Garcia", "target": "Late Night Study Session", "value": 4 },
        { "source": "Carlos Garcia", "target": "Algorithms Midterm", "value": 3 },
        { "source": "Brenda Smith", "target": "Spring Formal", "value": 5 },
        { "source": "Carlos Garcia", "target": "Spring Formal", "value": 5 },
        { "source": "Diana Chen", "target": "Spring Formal", "value": 5 },
        { "source": "Lab Partner Chloe", "target": "Final Exams Week", "value": 4 },
        { "source": "TA David", "target": "Late Night Study Session", "value": 3 },
        { "source": "RA Maria", "target": "Dorm Move-in Day", "value": 5 },
        { "source": "Brenda Smith", "target": "Graduation Ceremony", "value": 5 },
        { "source": "Carlos Garcia", "target": "Graduation Ceremony", "value": 5 },
        { "source": "Diana Chen", "target": "Graduation Ceremony", "value": 5 },
        { "source": "Roommate Sam", "target": "Graduation Ceremony", "value": 5 },
        { "source": "Prof. Evelyn Reed", "target": "Graduation Ceremony", "value": 4 },
        { "source": "Prof. Brian Carter", "target": "Graduation Ceremony", "value": 4 },
        { "source": "Manager at TechCorp", "target": "Graduation Ceremony", "value": 2 },
        { "source": "Mom", "target": "Graduation Ceremony", "value": 5 },
        { "source": "Dad", "target": "Graduation Ceremony", "value": 5 },
        { "source": "Sibling Jordan", "target": "Graduation Ceremony", "value": 5 },
        { "source": "Aaron Bell", "target": "Club Fair", "value": 2 },
        { "source": "Abigail Coleman", "target": "Club Fair", "value": 2 },
        { "source": "Adam Cox", "target": "Club Fair", "value": 2 },
        { "source": "Alice Flores", "target": "Weekend Picnic", "value": 3 },
        { "source": "Andrew Foster", "target": "Weekend Picnic", "value": 3 },
        { "source": "Angela Gray", "target": "Weekend Picnic", "value": 3 },
        { "source": "Anthony Griffin", "target": "Friday Movie Night", "value": 2 },
        { "source": "Barbara Hayes", "target": "Friday Movie Night", "value": 2 },
        { "source": "Benjamin Howard", "target": "Friday Movie Night", "value": 2 },
        { "source": "Betty Hughes", "target": "Orchestra Concert", "value": 1 },
        { "source": "Brandon James", "target": "Orchestra Concert", "value": 1 },
        { "source": "Brenda Jenkins", "target": "Orchestra Concert", "value": 1 },
        { "source": "Brian Johnson", "target": "Team Lunch", "value": 2 },
        { "source": "Carol Kelly", "target": "Team Lunch", "value": 2 },
        { "source": "Charles Kim", "target": "Team Lunch", "value": 2 },
        { "source": "Cynthia Long", "target": "Poetry Reading Night", "value": 3 },
        { "source": "Daniel Lopez", "target": "Poetry Reading Night", "value": 3 },
        { "source": "David Mitchell", "target": "Poetry Reading Night", "value": 3 },
        { "source": "Deborah Morgan", "target": "General Chemistry Lecture", "value": 2 },
        { "source": "Dennis Murphy", "target": "General Chemistry Lecture", "value": 2 },
        { "source": "Donald Murray", "target": "General Chemistry Lecture", "value": 2 },
        { "source": "Donna Myers", "target": "Fall Semester Kick-off", "value": 3 },
        { "source": "Edward Nelson", "target": "Fall Semester Kick-off", "value": 3 },
        { "source": "Elizabeth Ortiz", "target": "Fall Semester Kick-off", "value": 3 },
        { "source": "Frank Parker", "target": "Tennis Match", "value": 2 },
        { "source": "Gary Perry", "target": "Tennis Match", "value": 2 },
        { "source": "George Peterson", "target": "Tennis Match", "value": 2 },
        { "source": "Helen Phillips", "target": "Morning Workout", "value": 1 },
        { "source": "Henry Powell", "target": "Morning Workout", "value": 1 },
        { "source": "Irene Price", "target": "Morning Workout", "value": 1 },
        { "source": "Jack Reed", "target": "Hackathon", "value": 4 },
        { "source": "James Richardson", "target": "Hackathon", "value": 4 },
        { "source": "Janet Rivera", "target": "Hackathon", "value": 4 },
        { "source": "Jason Rogers", "target": "Coffee & Code Meetup", "value": 3 },
        { "source": "Jerry Ross", "target": "Coffee & Code Meetup", "value": 3 },
        { "source": "Joan Russell", "target": "Coffee & Code Meetup", "value": 3 },
        { "source": "Joe Sanchez", "target": "Spring Formal", "value": 4 },
        { "source": "John Sanders", "target": "Spring Formal", "value": 4 },
        { "source": "Joyce Scott", "target": "Spring Formal", "value": 4 },
        { "source": "Judith Simmons", "target": "Final Exams Week", "value": 3 },
        { "source": "Julie Stewart", "target": "Final Exams Week", "value": 3 },
        { "source": "Justin Stone", "target": "Final Exams Week", "value": 3 },
        { "source": "Karen Sullivan", "target": "Dorm Move-in Day", "value": 2 },
        { "source": "Katherine Taylor", "target": "Dorm Move-in Day", "value": 2 },
        { "source": "Keith Thomas", "target": "Dorm Move-in Day", "value": 2 },
        { "source": "Kelly Thompson", "target": "Student Gov. Meeting", "value": 3 },
        { "source": "Kenneth Turner", "target": "Student Gov. Meeting", "value": 3 },
        { "source": "Kimberly Walker", "target": "Student Gov. Meeting", "value": 3 },
        { "source": "Larry Watson", "target": "Resume Workshop", "value": 2 },
        { "source": "Laura West", "target": "Resume Workshop", "value": 2 },
        { "source": "Aaron Bell", "target": "Computer Science Dept.", "value": 2 },
        { "source": "Abigail Coleman", "target": "Student Union", "value": 3 },
        { "source": "Adam Cox", "target": "Main Campus Quad", "value": 4 },
        { "source": "Alice Flores", "target": "City Park", "value": 3 },
        { "source": "Andrew Foster", "target": "Dining Commons", "value": 4 },
        { "source": "Angela Gray", "target": "University Library", "value": 2 },
        { "source": "Anthony Griffin", "target": "Dorm Common Room", "value": 5 },
        { "source": "Barbara Hayes", "target": "Campus Theater", "value": 2 },
        { "source": "Benjamin Howard", "target": "Recreation Center", "value": 3 },
        { "source": "Betty Hughes", "target": "Music Hall", "value": 2 },
        { "source": "Brandon James", "target": "Art Studio", "value": 1 },
        { "source": "Brenda Jenkins", "target": "Local Bookstore", "value": 3 },
        { "source": "Brian Johnson", "target": "Off-Campus Coffee Shop", "value": 4 },
        { "source": "Carol Kelly", "target": "Student Dormitory 'Oak Hall'", "value": 5 },
        { "source": "Charles Kim", "target": "Lecture Hall B", "value": 2 },
        { "source": "Cynthia Long", "target": "Local Bookstore", "value": 4 },
        { "source": "Daniel Lopez", "target": "Main Campus Quad", "value": 3 },
        { "source": "David Mitchell", "target": "University Library", "value": 4 },
        { "source": "Deborah Morgan", "target": "Biology Lab", "value": 2 },
        { "source": "Dennis Murphy", "target": "Dining Commons", "value": 3 },
        { "source": "Donald Murray", "target": "Recreation Center", "value": 1 },
        { "source": "Donna Myers", "target": "Student Union", "value": 4 },
        { "source": "Edward Nelson", "target": "Main Campus Quad", "value": 3 },
        { "source": "Elizabeth Ortiz", "target": "Dorm Common Room", "value": 4 },
        { "source": "Frank Parker", "target": "Tennis Courts", "value": 3 },
        { "source": "Gary Perry", "target": "Recreation Center", "value": 2 },
        { "source": "George Peterson", "target": "Main Campus Quad", "value": 3 },
        { "source": "Helen Phillips", "target": "University Pool", "value": 2 },
        { "source": "Henry Powell", "target": "City Park", "value": 1 },
        { "source": "Irene Price", "target": "Art Studio", "value": 2 },
        { "source": "Jack Reed", "target": "Computer Science Dept.", "value": 4 },
        { "source": "James Richardson", "target": "University Library", "value": 3 },
        { "source": "Janet Rivera", "target": "Off-Campus Coffee Shop", "value": 2 },
        { "source": "Jason Rogers", "target": "Student Union", "value": 4 },
        { "source": "Jerry Ross", "target": "Dining Commons", "value": 3 },
        { "source": "Joan Russell", "target": "Main Campus Quad", "value": 2 },
        { "source": "Joe Sanchez", "target": "Student Dormitory 'Oak Hall'", "value": 4 },
        { "source": "John Sanders", "target": "Dorm Common Room", "value": 3 },
        { "source": "Joyce Scott", "target": "Campus Theater", "value": 2 },
        { "source": "Judith Simmons", "target": "University Library", "value": 4 },
        { "source": "Julie Stewart", "target": "Lecture Hall B", "value": 2 },
        { "source": "Justin Stone", "target": "Main Campus Quad", "value": 3 },
        { "source": "Karen Sullivan", "target": "Student Union", "value": 2 },
        { "source": "Katherine Taylor", "target": "Dining Commons", "value": 4 },
        { "source": "Keith Thomas", "target": "Recreation Center", "value": 1 },
        { "source": "Kelly Thompson", "target": "Student Union", "value": 4 },
        { "source": "Kenneth Turner", "target": "Main Campus Quad", "value": 3 },
        { "source": "Kimberly Walker", "target": "City Park", "value": 2 },
        { "source": "Larry Watson", "target": "Career Services Center", "value": 3 },
        { "source": "Laura West", "target": "University Library", "value": 2 }
    ]
}